aws_serverless_wrapper/__init__.py
aws_serverless_wrapper/__main__.py
aws_serverless_wrapper/_body_parsing.py
aws_serverless_wrapper/_environ_variables.py
aws_serverless_wrapper/base_class.py
aws_serverless_wrapper/error_logging.py
aws_serverless_wrapper/serverless_handler.py
aws_serverless_wrapper/wrapper.py
aws_serverless_wrapper/wrapper_config_schema.json
aws_serverless_wrapper/testing/__init__.py
aws_serverless_wrapper/testing/context.py
aws_serverless_wrapper/testing/event.py
tests/__init__.py
tests/test_main.py
tests/testing/__init__.py
tests/testing/test_context.py
tests/testing/test_event.py
tests/wrapper/__init__.py
tests/wrapper/test_api_responses.py
tests/wrapper/test_body_parsing.py
tests/wrapper/test_environ_variables.py
tests/wrapper/test_error_logging.py
tests/wrapper/test_response_validation.py
tests/wrapper/test_serverless_handler.py
tests/wrapper/test_wrapper.py
aws_serverless_wrapper-0.2.1.dist-info/METADATA
aws_serverless_wrapper-0.2.1.dist-info/WHEEL
aws_serverless_wrapper-0.2.1.dist-info/top_level.txt
aws_serverless_wrapper-0.2.1.dist-info/RECORD
