Metadata-Version: 2.1
Name: aws-serverless-wrapper
Version: 0.2.1
Summary: decorator for speeding up aws serverless development & separating business from infrastructure code
Home-page: https://github.com/janluak/aws-serverless-wrapper
Author: Jan Lukas Braje
Author-email: aws-serverless-wrapper@getkahawa.com
License: UNKNOWN
Platform: UNKNOWN
Classifier: Development Status :: 3 - Alpha
Classifier: Intended Audience :: Information Technology
Classifier: License :: OSI Approved :: Apache Software License
Classifier: Operating System :: OS Independent
Classifier: Programming Language :: Python :: 3.8
Requires-Python: >=3.8
Requires-Dist: boto3
Requires-Dist: jsonschema
Requires-Dist: botocore
